LICENSE.txt
MANIFEST.in
README.md
pyproject.toml
requirements.txt
setup.py
ginger_anchors/__init__.py
ginger_anchors/analysis.py
ginger_anchors/bo_search.py
ginger_anchors/custom_anchor.py
ginger_anchors/explainer.py
ginger_anchors/lucb.py
ginger_anchors/utils.py
ginger_anchors.egg-info/PKG-INFO
ginger_anchors.egg-info/SOURCES.txt
ginger_anchors.egg-info/dependency_links.txt
ginger_anchors.egg-info/requires.txt
ginger_anchors.egg-info/top_level.txt