Metadata-Version: 2.1
Name: ginger-anchors
Version: 0.1
Summary: Reimplementation of Anchors: High-Precision Model-Agnostic Explanations.
Home-page: https://www.automl.org
Author: Jim Rhotert and Julian Bilsky
Author-email: rhotert@stud.uni-hannover.de
License: Apache-2.0
Project-URL: Source Code, https://github.com/LUH-AI/ginger_anchors
Platform: Linux
Classifier: Programming Language :: Python :: 3.9
Classifier: Programming Language :: Python :: 3.10
Classifier: Natural Language :: English
Classifier: Intended Audience :: Developers
Classifier: Intended Audience :: Education
Classifier: Intended Audience :: Science/Research
Classifier: Topic :: Scientific/Engineering
Classifier: Topic :: Scientific/Engineering :: Artificial Intelligence
Requires-Python: >=3.9
Provides-Extra: dev
License-File: LICENSE.txt
